{
  "name": "esb-led~0001",
  "data": [
    {
      "seriesName": "SEAI_BIOENERGY",
      "seriesValues": [
        [
          2018,
          31.900977155527006
        ],
        [
          2019,
          32.22847751444473
        ],
        [
          2020,
          32.701798833537524
        ],
        [
          2021,
          32.46305328730375
        ],
        [
          2022,
          34.65873154705138
        ],
        [
          2023,
          36.432467302096256
        ],
        [
          2024,
          37.3633727315658
        ],
        [
          2025,
          37.57645292126683
        ],
        [
          2026,
          42.808130492491955
        ],
        [
          2027,
          52.61790059706526
        ],
        [
          2028,
          56.742719321965055
        ],
        [
          2029,
          59.35534782230184
        ],
        [
          2030,
          59.75770962679108
        ],
        [
          2031,
          59.57780066415762
        ],
        [
          2032,
          59.880463186894346
        ],
        [
          2033,
          61.981793351829964
        ],
        [
          2034,
          61.3648379584731
        ],
        [
          2035,
          62.19749126546968
        ],
        [
          2036,
          60.72761411913041
        ],
        [
          2037,
          61.59503003943444
        ],
        [
          2038,
          56.281986810643645
        ],
        [
          2039,
          55.90844458225779
        ],
        [
          2040,
          56.53888356377064
        ],
        [
          2041,
          56.8210111921524
        ],
        [
          2042,
          55.37924820835964
        ],
        [
          2043,
          54.19535313558478
        ],
        [
          2044,
          52.19003940468194
        ],
        [
          2045,
          51.4410019079925
        ],
        [
          2046,
          49.9726023059271
        ],
        [
          2047,
          49.14688836493211
        ],
        [
          2048,
          48.420768148101814
        ],
        [
          2049,
          48.41857644815829
        ],
        [
          2050,
          48.71935154854205
        ],
        [
          2051,
          48.73842763996447
        ]
      ]
    },
    {
      "seriesName": "SEAI_COAL",
      "seriesValues": [
        [
          2018,
          39.948410265588095
        ],
        [
          2019,
          18.5683897317412
        ],
        [
          2020,
          20.507211328799578
        ],
        [
          2021,
          40.41773398073708
        ],
        [
          2022,
          31.43785451189102
        ],
        [
          2023,
          8.850960065429318
        ],
        [
          2024,
          8.798450360778999
        ],
        [
          2025,
          6.865787312320071
        ],
        [
          2026,
          6.3576489543427845
        ],
        [
          2027,
          6.037042956158173
        ],
        [
          2028,
          5.164999647845019
        ],
        [
          2029,
          5.008499622364528
        ],
        [
          2030,
          4.851999656675107
        ],
        [
          2031,
          4.6954996947483
        ],
        [
          2032,
          4.538999715071428
        ],
        [
          2033,
          3.60000000482354
        ],
        [
          2034,
          3.28242312175491
        ],
        [
          2035,
          2.91770943290613
        ],
        [
          2036,
          2.55299574408282
        ],
        [
          2037,
          2.18828205536247
        ],
        [
          2038,
          1.82356836633762
        ],
        [
          2039,
          1.45885467801291
        ],
        [
          2040,
          1.09414098996936
        ],
        [
          2041,
          0.72942730243068
        ],
        [
          2042,
          0.364713616203242
        ],
        [
          2045,
          0.0
        ],
        [
          2046,
          0.0
        ],
        [
          2047,
          0.0
        ],
        [
          2048,
          0.0
        ],
        [
          2049,
          0.0
        ],
        [
          2050,
          0.0
        ],
        [
          2051,
          0.0
        ]
      ]
    },
    {
      "seriesName": "SEAI_ELECTRICITY",
      "seriesValues": [
        [
          2018,
          -0.09984571704603695
        ],
        [
          2019,
          2.320763101542534
        ],
        [
          2020,
          -0.546772117212246
        ],
        [
          2021,
          5.716363954877702
        ],
        [
          2022,
          0.9069960296091457
        ],
        [
          2023,
          6.000000024284644
        ],
        [
          2024,
          6.00000002417276
        ],
        [
          2025,
          6.000000024135875
        ],
        [
          2026,
          6.0000000241565346
        ],
        [
          2027,
          6.000000021614148
        ],
        [
          2028,
          6.000000029048911
        ],
        [
          2029,
          6.000000016910696
        ],
        [
          2030,
          6.000000009534143
        ],
        [
          2031,
          -18.052304318377562
        ],
        [
          2032,
          -19.87945744680283
        ],
        [
          2033,
          -20.148514794946223
        ],
        [
          2034,
          -22.533143186009642
        ],
        [
          2035,
          -22.43724583043496
        ],
        [
          2036,
          -20.9917547545214
        ],
        [
          2037,
          -22.1651969267296
        ],
        [
          2038,
          -24.951832337361722
        ],
        [
          2039,
          -26.246610590938563
        ],
        [
          2040,
          -26.43415181868424
        ],
        [
          2041,
          -26.3304847177796
        ],
        [
          2042,
          -26.744230119219445
        ],
        [
          2043,
          -26.591331785882858
        ],
        [
          2044,
          -29.403403522523014
        ],
        [
          2045,
          -30.297141914077137
        ],
        [
          2046,
          -31.328239916748284
        ],
        [
          2047,
          -33.171112004638736
        ],
        [
          2048,
          -35.24088267797773
        ],
        [
          2049,
          -37.625828677729096
        ],
        [
          2050,
          -39.58619582547911
        ],
        [
          2051,
          -39.658083902556776
        ]
      ]
    },
    {
      "seriesName": "SEAI_NATGAS",
      "seriesValues": [
        [
          2018,
          185.3730725058083
        ],
        [
          2019,
          190.80996265503302
        ],
        [
          2020,
          198.11081190258
        ],
        [
          2021,
          181.597291383437
        ],
        [
          2022,
          197.5804463777802
        ],
        [
          2023,
          199.43976416666422
        ],
        [
          2024,
          197.27932936602608
        ],
        [
          2025,
          185.58243725831738
        ],
        [
          2026,
          177.869051386429
        ],
        [
          2027,
          167.815481271075
        ],
        [
          2028,
          147.297567063559
        ],
        [
          2029,
          88.2956072366987
        ],
        [
          2030,
          45.4979976659435
        ],
        [
          2031,
          37.80679843415883
        ],
        [
          2032,
          32.81460661985496
        ],
        [
          2033,
          27.8851483468573
        ],
        [
          2034,
          21.7159660251702
        ],
        [
          2035,
          17.9192624096725
        ],
        [
          2036,
          15.4550182794599
        ],
        [
          2037,
          12.9765394553323
        ],
        [
          2038,
          10.4635377585863
        ],
        [
          2039,
          9.23556897538887
        ],
        [
          2040,
          7.09044404430444
        ],
        [
          2041,
          4.49046313019982
        ],
        [
          2042,
          2.23126274821866
        ],
        [
          2043,
          0.251517843258362
        ],
        [
          2044,
          3.792063659577682e-06
        ],
        [
          2045,
          1.5377247448291714e-06
        ],
        [
          2046,
          0.03048798188334684
        ],
        [
          2047,
          0.0
        ],
        [
          2048,
          0.0
        ],
        [
          2049,
          0.0039170054362564
        ],
        [
          2050,
          0.0092269081174383
        ],
        [
          2051,
          0.0092269181709904
        ]
      ]
    },
    {
      "seriesName": "SEAI_OIL",
      "seriesValues": [
        [
          2018,
          300.9542563873898
        ],
        [
          2019,
          301.4522884354055
        ],
        [
          2020,
          250.74249606949104
        ],
        [
          2021,
          265.55408056759853
        ],
        [
          2022,
          290.7129402539439
        ],
        [
          2023,
          253.02198199029584
        ],
        [
          2024,
          238.67640982262517
        ],
        [
          2025,
          227.63125174867724
        ],
        [
          2026,
          211.60193360750753
        ],
        [
          2027,
          191.47982603104282
        ],
        [
          2028,
          179.01111258977488
        ],
        [
          2029,
          163.80297699943569
        ],
        [
          2030,
          144.3585259322362
        ],
        [
          2031,
          127.0689132037036
        ],
        [
          2032,
          118.27419912412834
        ],
        [
          2033,
          103.92776386788094
        ],
        [
          2034,
          90.5113873951954
        ],
        [
          2035,
          77.67098816510313
        ],
        [
          2036,
          67.56900856264497
        ],
        [
          2037,
          61.53860518638322
        ],
        [
          2038,
          58.68901725787674
        ],
        [
          2039,
          55.19592772394182
        ],
        [
          2040,
          53.15442874931982
        ],
        [
          2041,
          51.53050071285739
        ],
        [
          2042,
          50.84169394807783
        ],
        [
          2043,
          52.16979820999477
        ],
        [
          2044,
          50.52352625981757
        ],
        [
          2045,
          49.365379637993506
        ],
        [
          2046,
          48.21297718706825
        ],
        [
          2047,
          46.99216226970523
        ],
        [
          2048,
          45.954175500582174
        ],
        [
          2049,
          44.87575240623027
        ],
        [
          2050,
          44.22408339812875
        ],
        [
          2051,
          44.044103738780485
        ]
      ]
    },
    {
      "seriesName": "SEAI_OTHER_RENEWABLES",
      "seriesValues": [
        [
          2018,
          37.26949532578647
        ],
        [
          2019,
          41.48314115599361
        ],
        [
          2020,
          45.71881367041168
        ],
        [
          2021,
          48.07138089268085
        ],
        [
          2022,
          57.919629609465034
        ],
        [
          2023,
          71.39260437436627
        ],
        [
          2024,
          80.83191406494831
        ],
        [
          2025,
          92.65267313873127
        ],
        [
          2026,
          101.38283217240017
        ],
        [
          2027,
          110.07810595907864
        ],
        [
          2028,
          126.6042337455484
        ],
        [
          2029,
          166.2250335267972
        ],
        [
          2030,
          206.07858460437504
        ],
        [
          2031,
          242.8494752638775
        ],
        [
          2032,
          249.59346743896032
        ],
        [
          2033,
          255.82680001489805
        ],
        [
          2034,
          265.2450901004184
        ],
        [
          2035,
          269.86858264758894
        ],
        [
          2036,
          273.92437294740165
        ],
        [
          2037,
          275.9091098667379
        ],
        [
          2038,
          284.69266854397097
        ],
        [
          2039,
          287.58067062063134
        ],
        [
          2040,
          289.14477458218596
        ],
        [
          2041,
          290.35427023496544
        ],
        [
          2042,
          292.11297130773266
        ],
        [
          2043,
          293.54181225737085
        ],
        [
          2044,
          298.33003702163364
        ],
        [
          2045,
          298.3410292271949
        ],
        [
          2046,
          298.72878611881634
        ],
        [
          2047,
          299.4437662163985
        ],
        [
          2048,
          300.7013117903993
        ],
        [
          2049,
          301.75397216593774
        ],
        [
          2050,
          302.53807207431083
        ],
        [
          2051,
          302.51156681686473
        ]
      ]
    },
    {
      "seriesName": "SEAI_PEAT",
      "seriesValues": [
        [
          2018,
          29.2326240284752
        ],
        [
          2019,
          26.9639999933027
        ],
        [
          2020,
          17.2899999980852
        ],
        [
          2021,
          10.597999995005
        ],
        [
          2022,
          8.91700000019699
        ],
        [
          2023,
          4.03166925622103
        ],
        [
          2024,
          3.99135254198246
        ],
        [
          2025,
          3.55540091055402
        ],
        [
          2026,
          2.98824984566666
        ],
        [
          2027,
          2.74414597587058
        ],
        [
          2028,
          0.0
        ],
        [
          2029,
          0.0
        ],
        [
          2030,
          0.0
        ],
        [
          2031,
          0.0
        ],
        [
          2032,
          0.0
        ],
        [
          2033,
          0.0
        ],
        [
          2034,
          0.0
        ],
        [
          2035,
          0.0
        ],
        [
          2036,
          0.0
        ],
        [
          2037,
          0.0
        ],
        [
          2046,
          0.0
        ],
        [
          2047,
          0.0
        ],
        [
          2048,
          0.0
        ],
        [
          2049,
          0.0
        ],
        [
          2050,
          0.0
        ],
        [
          2051,
          0.0
        ]
      ]
    }
  ]
}