{
  "name": "esb-bau~0003",
  "data": [
    {
      "seriesName": "DMD_TRA-P-ACTIVE",
      "seriesValues": [
        [
          2018,
          5.502380110970158
        ],
        [
          2019,
          5.623278620039985
        ],
        [
          2020,
          4.06776833142749
        ],
        [
          2021,
          5.130411053513365
        ],
        [
          2022,
          5.313447416783628
        ],
        [
          2023,
          5.3328025062430005
        ],
        [
          2024,
          5.3994625368894384
        ],
        [
          2025,
          5.4669558183158715
        ],
        [
          2026,
          5.53529276537871
        ],
        [
          2027,
          5.604483924155679
        ],
        [
          2028,
          5.674539972448874
        ],
        [
          2029,
          5.745471731561116
        ],
        [
          2030,
          5.817290127304143
        ],
        [
          2031,
          5.8900062530376225
        ],
        [
          2032,
          5.963631330316634
        ],
        [
          2033,
          6.038176721063607
        ],
        [
          2034,
          6.113653929207529
        ],
        [
          2035,
          6.1900746023579405
        ],
        [
          2036,
          6.267450534015612
        ],
        [
          2037,
          6.3457937140862155
        ],
        [
          2038,
          6.4251161340270055
        ],
        [
          2039,
          6.505430084171256
        ],
        [
          2040,
          6.586747958707809
        ],
        [
          2041,
          6.669082306680884
        ],
        [
          2042,
          6.752445834015453
        ],
        [
          2043,
          6.836851405435876
        ],
        [
          2044,
          6.922312046495882
        ],
        [
          2045,
          7.0088409454377505
        ],
        [
          2046,
          7.09645145585879
        ],
        [
          2047,
          7.18515709756258
        ],
        [
          2048,
          7.274971559575
        ],
        [
          2049,
          7.36590870253476
        ],
        [
          2050,
          7.45798255977091
        ],
        [
          2051,
          7.607579121654309
        ]
      ]
    },
    {
      "seriesName": "DMD_TRA-P-BUS",
      "seriesValues": [
        [
          2018,
          9.81689610820473
        ],
        [
          2019,
          9.589995958804172
        ],
        [
          2020,
          6.937213076791507
        ],
        [
          2021,
          7.833208297367277
        ],
        [
          2022,
          8.316536544823176
        ],
        [
          2023,
          8.346830869397701
        ],
        [
          2024,
          8.499943156015968
        ],
        [
          2025,
          8.656086472719775
        ],
        [
          2026,
          8.81532507505891
        ],
        [
          2027,
          8.97772470329428
        ],
        [
          2028,
          9.143352568330721
        ],
        [
          2029,
          9.312277355887911
        ],
        [
          2030,
          9.484569300617064
        ],
        [
          2031,
          9.660300243504093
        ],
        [
          2032,
          9.839543651468714
        ],
        [
          2033,
          10.02237457373922
        ],
        [
          2034,
          10.208869824812238
        ],
        [
          2035,
          10.399107927610595
        ],
        [
          2036,
          10.593169179007074
        ],
        [
          2037,
          10.791135689794242
        ],
        [
          2038,
          10.993091476721325
        ],
        [
          2039,
          11.199122313804404
        ],
        [
          2040,
          11.409316094446583
        ],
        [
          2041,
          11.623762591515053
        ],
        [
          2042,
          11.842553617201142
        ],
        [
          2043,
          12.065783122949322
        ],
        [
          2044,
          12.293547194429411
        ],
        [
          2045,
          12.52594410319143
        ],
        [
          2046,
          12.763074275746977
        ],
        [
          2047,
          13.005040556217123
        ],
        [
          2048,
          13.251947997843061
        ],
        [
          2049,
          13.503904150313595
        ],
        [
          2050,
          13.761019012386962
        ],
        [
          2051,
          13.938648813139434
        ]
      ]
    },
    {
      "seriesName": "DMD_TRA-P-CAR",
      "seriesValues": [
        [
          2018,
          53.68550243820114
        ],
        [
          2019,
          52.64476728529478
        ],
        [
          2020,
          38.02437903107009
        ],
        [
          2021,
          43.49127032436443
        ],
        [
          2022,
          46.32772429846444
        ],
        [
          2023,
          46.5523018004478
        ],
        [
          2024,
          47.43526971459383
        ],
        [
          2025,
          48.27229244818808
        ],
        [
          2026,
          49.12523804888133
        ],
        [
          2027,
          49.99443206832254
        ],
        [
          2028,
          50.88020756879268
        ],
        [
          2029,
          51.78290476983502
        ],
        [
          2030,
          52.702871277251084
        ],
        [
          2031,
          53.555729151264686
        ],
        [
          2032,
          54.50938466085958
        ],
        [
          2033,
          55.48135326214263
        ],
        [
          2034,
          56.47201304748245
        ],
        [
          2035,
          57.48175027282188
        ],
        [
          2036,
          58.51095976354623
        ],
        [
          2037,
          59.56004496189406
        ],
        [
          2038,
          60.62941828078372
        ],
        [
          2039,
          61.71950121397263
        ],
        [
          2040,
          62.830724415711714
        ],
        [
          2041,
          63.96352822929282
        ],
        [
          2042,
          65.11836260007976
        ],
        [
          2043,
          66.29568696580604
        ],
        [
          2044,
          67.49597226630425
        ],
        [
          2045,
          68.71969862180391
        ],
        [
          2046,
          69.9673571880018
        ],
        [
          2047,
          71.23945005018136
        ],
        [
          2048,
          72.5364904139514
        ],
        [
          2049,
          73.85900287090227
        ],
        [
          2050,
          75.20752379884122
        ],
        [
          2051,
          76.12814098422783
        ]
      ]
    },
    {
      "seriesName": "DMD_TRA-P-HPT",
      "seriesValues": [
        [
          2018,
          2.281087425734197
        ],
        [
          2019,
          2.1053822949040777
        ],
        [
          2020,
          1.522991842794499
        ],
        [
          2021,
          1.5470457501922281
        ],
        [
          2022,
          1.602239319342592
        ],
        [
          2023,
          1.6080757436068631
        ],
        [
          2024,
          1.648277625935128
        ],
        [
          2025,
          1.689484578835486
        ],
        [
          2026,
          1.7317216934301474
        ],
        [
          2027,
          1.775014733875477
        ],
        [
          2028,
          1.8193900987567848
        ],
        [
          2029,
          1.8648748487411568
        ],
        [
          2030,
          1.9114967177303979
        ],
        [
          2031,
          1.9592841342777318
        ],
        [
          2032,
          2.008266235969592
        ],
        [
          2033,
          2.058472889963957
        ],
        [
          2034,
          2.109934710027781
        ],
        [
          2035,
          2.162683075392905
        ],
        [
          2036,
          2.216750150103377
        ],
        [
          2037,
          2.2721689015924458
        ],
        [
          2038,
          2.328973136042894
        ],
        [
          2039,
          2.387197461314042
        ],
        [
          2040,
          2.4468773956173
        ],
        [
          2041,
          2.508049327955991
        ],
        [
          2042,
          2.570750558464506
        ],
        [
          2043,
          2.635019320003165
        ],
        [
          2044,
          2.700894800119305
        ],
        [
          2045,
          2.768417167050295
        ],
        [
          2046,
          2.837627592852649
        ],
        [
          2047,
          2.9085682805632818
        ],
        [
          2048,
          2.98128244489632
        ],
        [
          2049,
          3.05581450281302
        ],
        [
          2050,
          3.13220985716279
        ],
        [
          2051,
          3.18851287583296
        ]
      ]
    },
    {
      "seriesName": "DMD_TRA-P-LPT",
      "seriesValues": [
        [
          2018,
          0.317226564580658
        ],
        [
          2019,
          0.3429010167768512
        ],
        [
          2020,
          0.2480478106648861
        ],
        [
          2021,
          0.3025061750658214
        ],
        [
          2022,
          0.3238693799412613
        ],
        [
          2023,
          0.3250491258909334
        ],
        [
          2024,
          0.3296427031490522
        ],
        [
          2025,
          0.3343016587238265
        ],
        [
          2026,
          0.3390269263117973
        ],
        [
          2027,
          0.3438194569914456
        ],
        [
          2028,
          0.34868022703199353
        ],
        [
          2029,
          0.3536101893134654
        ],
        [
          2030,
          0.3586103481461193
        ],
        [
          2031,
          0.3636817100498454
        ],
        [
          2032,
          0.3688252944142594
        ],
        [
          2033,
          0.3740421370355463
        ],
        [
          2034,
          0.3793332881072826
        ],
        [
          2035,
          0.3846998128528498
        ],
        [
          2036,
          0.3901427921345358
        ],
        [
          2037,
          0.39566332211368416
        ],
        [
          2038,
          0.4012625394687204
        ],
        [
          2039,
          0.4069415231811594
        ],
        [
          2040,
          0.4127014422484845
        ],
        [
          2041,
          0.4185434575754769
        ],
        [
          2042,
          0.424468746826896
        ],
        [
          2043,
          0.4304785046442622
        ],
        [
          2044,
          0.4365739429191268
        ],
        [
          2045,
          0.4427562909063855
        ],
        [
          2046,
          0.4490268207681372
        ],
        [
          2047,
          0.4553867233256088
        ],
        [
          2048,
          0.461837331151351
        ],
        [
          2049,
          0.468379971197853
        ],
        [
          2050,
          0.475015939352057
        ],
        [
          2051,
          0.480090802742536
        ]
      ]
    },
    {
      "seriesName": "DMD_TRA-P-MOT",
      "seriesValues": [
        [
          2018,
          0.1208077502789526
        ],
        [
          2019,
          0.1232616791459991
        ],
        [
          2020,
          0.0903408683209436
        ],
        [
          2021,
          0.0955068383330559
        ],
        [
          2022,
          0.0811520638322258
        ],
        [
          2023,
          0.071754990149374
        ],
        [
          2024,
          0.0647945566962757
        ],
        [
          2025,
          0.059376520029678
        ],
        [
          2026,
          0.0548759610048763
        ],
        [
          2027,
          0.0506753022573142
        ],
        [
          2028,
          0.046141590262718996
        ],
        [
          2029,
          0.040679482854721505
        ],
        [
          2030,
          0.0338827438048789
        ],
        [
          2031,
          0.034146436142506266
        ],
        [
          2032,
          0.034658616960014675
        ],
        [
          2033,
          0.03517848896949948
        ],
        [
          2034,
          0.035706167983745256
        ],
        [
          2035,
          0.036241761073588084
        ],
        [
          2036,
          0.03678538882798419
        ],
        [
          2037,
          0.037337171112576985
        ],
        [
          2038,
          0.03789723025208323
        ],
        [
          2039,
          0.03846569028217432
        ],
        [
          2040,
          0.03904267972497781
        ],
        [
          2041,
          0.039628289690434464
        ],
        [
          2042,
          0.04022271907601053
        ],
        [
          2043,
          0.040826053959068395
        ],
        [
          2044,
          0.04143844575045233
        ],
        [
          2045,
          0.042060025084358736
        ],
        [
          2046,
          0.04269091832435446
        ],
        [
          2047,
          0.04333129323110344
        ],
        [
          2048,
          0.04398126350860896
        ],
        [
          2049,
          0.044641001304966454
        ],
        [
          2050,
          0.045310616557746174
        ],
        [
          2051,
          0.045583287272751134
        ]
      ]
    },
    {
      "seriesName": "DMD_TRA-P-TAXI",
      "seriesValues": [
        [
          2018,
          1.2403568124902906
        ],
        [
          2019,
          1.2002713994766794
        ],
        [
          2020,
          0.9248791746971055
        ],
        [
          2021,
          1.0768216144937874
        ],
        [
          2022,
          1.143848787989643
        ],
        [
          2023,
          1.101886889201986
        ],
        [
          2024,
          1.0653076789247156
        ],
        [
          2025,
          1.089044940097037
        ],
        [
          2026,
          1.1121811532018842
        ],
        [
          2027,
          1.1353392378762783
        ],
        [
          2028,
          1.15915836232172
        ],
        [
          2029,
          1.184239948501683
        ],
        [
          2030,
          1.2109965137071066
        ],
        [
          2031,
          1.3157726867976371
        ],
        [
          2032,
          1.3378435911313489
        ],
        [
          2033,
          1.3603122216102501
        ],
        [
          2034,
          1.383186269021341
        ],
        [
          2035,
          1.4064736405294511
        ],
        [
          2036,
          1.4301824202544258
        ],
        [
          2037,
          1.454320804271906
        ],
        [
          2038,
          1.4788972139652286
        ],
        [
          2039,
          1.5039201980599197
        ],
        [
          2040,
          1.5293986361406564
        ],
        [
          2041,
          1.5553413283942321
        ],
        [
          2042,
          1.581757452559987
        ],
        [
          2043,
          1.6086562622676401
        ],
        [
          2044,
          1.6360474329235917
        ],
        [
          2045,
          1.6639406478354428
        ],
        [
          2046,
          1.6923457866011546
        ],
        [
          2047,
          1.7212729927386625
        ],
        [
          2048,
          1.750732618093772
        ],
        [
          2049,
          1.7807352425987721
        ],
        [
          2050,
          1.8112917085174896
        ],
        [
          2051,
          1.832629943194716
        ]
      ]
    }
  ]
}