{
  "name": "esb-led~0003",
  "data": [
    {
      "seriesName": "DMD_TRA-F-HTRUCK",
      "seriesValues": [
        [
          2018,
          9.30279910714344
        ],
        [
          2019,
          9.26481582535491
        ],
        [
          2020,
          9.00569940406429
        ],
        [
          2021,
          9.30130219881474
        ],
        [
          2022,
          9.475192666390988
        ],
        [
          2023,
          9.38489022974988
        ],
        [
          2024,
          9.294587788069736
        ],
        [
          2025,
          9.204285342533582
        ],
        [
          2026,
          9.113982903260919
        ],
        [
          2027,
          9.023680457629684
        ],
        [
          2028,
          8.933378009743134
        ],
        [
          2029,
          8.84307555777489
        ],
        [
          2030,
          8.75277304221272
        ],
        [
          2031,
          8.72669447560026
        ],
        [
          2032,
          8.700616007201738
        ],
        [
          2033,
          8.67453745480183
        ],
        [
          2034,
          8.648458900747789
        ],
        [
          2035,
          8.622380445978978
        ],
        [
          2036,
          8.596301906286278
        ],
        [
          2037,
          8.57022336682318
        ],
        [
          2038,
          8.544144827659444
        ],
        [
          2039,
          8.518066287093914
        ],
        [
          2040,
          8.491987745661612
        ],
        [
          2041,
          8.465909207635722
        ],
        [
          2042,
          8.439830668195778
        ],
        [
          2043,
          8.41375212827699
        ],
        [
          2044,
          8.387673588359327
        ],
        [
          2045,
          8.36159505180693
        ],
        [
          2046,
          8.335516510431457
        ],
        [
          2047,
          8.309437945748869
        ],
        [
          2048,
          8.28335940805482
        ],
        [
          2049,
          8.257280875771826
        ],
        [
          2050,
          8.231202347936799
        ],
        [
          2051,
          8.23120234884437
        ]
      ]
    },
    {
      "seriesName": "DMD_TRA-F-LTRUCK",
      "seriesValues": [
        [
          2018,
          0.268742059407103
        ],
        [
          2019,
          0.2676447873456851
        ],
        [
          2020,
          0.26015935414293273
        ],
        [
          2021,
          0.2686988167727094
        ],
        [
          2022,
          0.2737222175313541
        ],
        [
          2023,
          0.2711135329626672
        ],
        [
          2024,
          0.26850484940034036
        ],
        [
          2025,
          0.2658961644711863
        ],
        [
          2026,
          0.26328748036743294
        ],
        [
          2027,
          0.2606787963020457
        ],
        [
          2028,
          0.25807011237890803
        ],
        [
          2029,
          0.25546142873549355
        ],
        [
          2030,
          0.2528527449789027
        ],
        [
          2031,
          0.25209937985403585
        ],
        [
          2032,
          0.25134601518648286
        ],
        [
          2033,
          0.2505926505133085
        ],
        [
          2034,
          0.24983928585774937
        ],
        [
          2035,
          0.24908592119280049
        ],
        [
          2036,
          0.24833255651685823
        ],
        [
          2037,
          0.24757919170835235
        ],
        [
          2038,
          0.246825826918573
        ],
        [
          2039,
          0.24607246223288554
        ],
        [
          2040,
          0.24531909756462927
        ],
        [
          2041,
          0.24456573285935243
        ],
        [
          2042,
          0.24381236788257113
        ],
        [
          2043,
          0.24305900252672188
        ],
        [
          2044,
          0.24230563782607914
        ],
        [
          2045,
          0.24155227310853566
        ],
        [
          2046,
          0.240798908396816
        ],
        [
          2047,
          0.24004554376147558
        ],
        [
          2048,
          0.23929217900821265
        ],
        [
          2049,
          0.23853881417933384
        ],
        [
          2050,
          0.237785449872006
        ],
        [
          2051,
          0.23778544918823707
        ]
      ]
    },
    {
      "seriesName": "DMD_TRA-F-MTRUCK",
      "seriesValues": [
        [
          2018,
          1.04938904579224
        ],
        [
          2019,
          1.04510439559088
        ],
        [
          2020,
          1.0158751354491449
        ],
        [
          2021,
          1.0492201894959643
        ],
        [
          2022,
          1.0688356569984054
        ],
        [
          2023,
          1.0586492176679554
        ],
        [
          2024,
          1.0484627797486679
        ],
        [
          2025,
          1.0382763385385796
        ],
        [
          2026,
          1.0280898994652712
        ],
        [
          2027,
          1.0179034591875646
        ],
        [
          2028,
          1.0077170193930307
        ],
        [
          2029,
          0.9975305771039815
        ],
        [
          2030,
          0.9873441317445678
        ],
        [
          2031,
          0.984402380070292
        ],
        [
          2032,
          0.9814606252267523
        ],
        [
          2033,
          0.9785188666561947
        ],
        [
          2034,
          0.9755771063194898
        ],
        [
          2035,
          0.9726353434681178
        ],
        [
          2036,
          0.9696935887346031
        ],
        [
          2037,
          0.9667518334471839
        ],
        [
          2038,
          0.9638100777870027
        ],
        [
          2039,
          0.9608683504623338
        ],
        [
          2040,
          0.9579265953097177
        ],
        [
          2041,
          0.9549848368961183
        ],
        [
          2042,
          0.9520431178330505
        ],
        [
          2043,
          0.9491013647048191
        ],
        [
          2044,
          0.9461595858942833
        ],
        [
          2045,
          0.9432178319102982
        ],
        [
          2046,
          0.9402760796358518
        ],
        [
          2047,
          0.9373343273402452
        ],
        [
          2048,
          0.9343925784905394
        ],
        [
          2049,
          0.9314508319179755
        ],
        [
          2050,
          0.9285090886582492
        ],
        [
          2051,
          0.928509091627971
        ]
      ]
    },
    {
      "seriesName": "DMD_TRA-F-TRAIN",
      "seriesValues": [
        [
          2018,
          0.08166076945059
        ],
        [
          2019,
          0.0610349734130404
        ],
        [
          2020,
          0.0664660894133415
        ],
        [
          2021,
          0.059328777496704
        ],
        [
          2022,
          0.060437943096247705
        ],
        [
          2023,
          0.0598619392876589
        ],
        [
          2024,
          0.0592859409115461
        ],
        [
          2025,
          0.0587099419317949
        ],
        [
          2026,
          0.0581339435636297
        ],
        [
          2027,
          0.0575579451901734
        ],
        [
          2028,
          0.0569819465766194
        ],
        [
          2029,
          0.056405948239926
        ],
        [
          2030,
          0.0558299508270912
        ],
        [
          2031,
          0.0556636058073809
        ],
        [
          2032,
          0.0554972628769171
        ],
        [
          2033,
          0.0553309195022639
        ],
        [
          2034,
          0.055164577203102
        ],
        [
          2035,
          0.0549982346431342
        ],
        [
          2036,
          0.0548318907618405
        ],
        [
          2037,
          0.0546655486159511
        ],
        [
          2038,
          0.0544992048323521
        ],
        [
          2039,
          0.0543328610101227
        ],
        [
          2040,
          0.0541665202814773
        ],
        [
          2041,
          0.0540001765003335
        ],
        [
          2042,
          0.0538338334079395
        ],
        [
          2043,
          0.0536674926351379
        ],
        [
          2044,
          0.0535011487392559
        ],
        [
          2045,
          0.0533348037226152
        ],
        [
          2046,
          0.0531684576773301
        ],
        [
          2047,
          0.0530021130232963
        ],
        [
          2048,
          0.0528357727832768
        ],
        [
          2049,
          0.0526693455525929
        ],
        [
          2050,
          0.0525030499352799
        ],
        [
          2051,
          0.0525030477018293
        ]
      ]
    }
  ]
}