{
  "name": "esb-bau~0002",
  "data": [
    {
      "seriesName": "FT_IND",
      "seriesValues": [
        [
          2018,
          9.11784211515054
        ],
        [
          2019,
          4.08
        ],
        [
          2020,
          3.84
        ],
        [
          2021,
          3.1437010233875
        ],
        [
          2022,
          3.6
        ],
        [
          2023,
          3.6
        ],
        [
          2024,
          3.6
        ],
        [
          2025,
          3.6
        ],
        [
          2026,
          3.6
        ],
        [
          2027,
          3.6
        ],
        [
          2028,
          3.6
        ],
        [
          2029,
          3.6
        ],
        [
          2030,
          3.6
        ],
        [
          2031,
          3.6
        ],
        [
          2032,
          3.6
        ],
        [
          2033,
          3.6
        ],
        [
          2034,
          3.28242281016085
        ],
        [
          2035,
          2.91770909801291
        ],
        [
          2036,
          2.55299538851064
        ],
        [
          2037,
          2.1882816755742
        ],
        [
          2038,
          1.82356796065683
        ],
        [
          2039,
          1.458854245069
        ],
        [
          2040,
          1.09414052931551
        ],
        [
          2041,
          0.729426813040038
        ],
        [
          2042,
          0.364713101266889
        ],
        [
          2045,
          0.0
        ],
        [
          2046,
          0.0
        ],
        [
          2047,
          0.0
        ],
        [
          2048,
          0.0
        ],
        [
          2049,
          0.0
        ],
        [
          2050,
          0.0
        ],
        [
          2051,
          0.0
        ]
      ]
    },
    {
      "seriesName": "FT_RSD",
      "seriesValues": [
        [
          2018,
          9.281999985520377
        ],
        [
          2019,
          7.95599998794998
        ],
        [
          2020,
          8.035999993691405
        ],
        [
          2021,
          7.643999994841954
        ],
        [
          2022,
          5.303999992939644
        ],
        [
          2023,
          0.0017484927986353913
        ],
        [
          2024,
          0.0
        ]
      ]
    },
    {
      "seriesName": "FT_SRV",
      "seriesValues": [
        [
          2018,
          0.02356813963266494
        ],
        [
          2019,
          0.02238973081995521
        ],
        [
          2020,
          0.021211326496252687
        ],
        [
          2021,
          0.02003290962367447
        ],
        [
          2022,
          0.01885451310269351
        ]
      ]
    }
  ]
}