{
  "name": "esb-led~0002",
  "data": [
    {
      "seriesName": "DMD_TRA-F-HTRUCK-ICE",
      "seriesValues": [
        [
          2018,
          21.648
        ],
        [
          2019,
          23.8425
        ],
        [
          2020,
          24.338999986141502
        ],
        [
          2021,
          23.813691395803062
        ],
        [
          2022,
          23.14710291338507
        ],
        [
          2023,
          23.31477525957929
        ],
        [
          2024,
          22.66874269993535
        ],
        [
          2025,
          20.96678514090179
        ],
        [
          2026,
          19.6739330936803
        ],
        [
          2027,
          18.409112824167867
        ],
        [
          2028,
          17.5135653740197
        ],
        [
          2029,
          16.24487071582594
        ],
        [
          2030,
          14.25114076382151
        ],
        [
          2031,
          13.20534485786587
        ],
        [
          2032,
          11.70142525054681
        ],
        [
          2033,
          9.84961991496328
        ],
        [
          2034,
          7.72423616769397
        ],
        [
          2035,
          5.574273346643889
        ],
        [
          2036,
          3.69042393884317
        ],
        [
          2037,
          2.2356414971155796
        ],
        [
          2038,
          1.2366315616433698
        ],
        [
          2039,
          0.6234465939137268
        ],
        [
          2040,
          0.285979744236802
        ],
        [
          2041,
          0.11910699245545106
        ],
        [
          2042,
          0.044873261991260155
        ],
        [
          2043,
          0.0
        ],
        [
          2044,
          0.0
        ],
        [
          2049,
          0.0
        ],
        [
          2050,
          0.0
        ],
        [
          2051,
          0.0
        ]
      ]
    },
    {
      "seriesName": "DMD_TRA-F-HTRUCK-BEV",
      "seriesValues": [
        [
          2025,
          0.379500000066969
        ],
        [
          2026,
          0.838187410911258
        ],
        [
          2027,
          1.66983751526
        ],
        [
          2028,
          2.40063207303917
        ],
        [
          2029,
          3.50895678355402
        ],
        [
          2030,
          7.39741356674263
        ],
        [
          2031,
          14.8403366250392
        ],
        [
          2032,
          20.0706797607196
        ],
        [
          2033,
          20.0105214928313
        ],
        [
          2034,
          19.9503632195658
        ],
        [
          2035,
          19.8902049442219
        ],
        [
          2036,
          19.8300466697931
        ],
        [
          2037,
          19.7698883908265
        ],
        [
          2038,
          19.7097301031873
        ],
        [
          2039,
          19.6495718038293
        ],
        [
          2040,
          19.5894134877551
        ],
        [
          2041,
          19.5292551719833
        ],
        [
          2042,
          19.4690968415279
        ],
        [
          2043,
          19.4089384998583
        ],
        [
          2044,
          19.3487801910696
        ],
        [
          2045,
          19.2886218830094
        ],
        [
          2046,
          19.2284635478618
        ],
        [
          2047,
          19.1683051532709
        ],
        [
          2048,
          19.108146772932738
        ],
        [
          2049,
          19.047988374543653
        ],
        [
          2050,
          18.98782996545826
        ],
        [
          2051,
          18.98782980042859
        ]
      ]
    },
    {
      "seriesName": "DMD_TRA-F-HTRUCK-HEV",
      "seriesValues": [
        [
          2025,
          0.30360000020239
        ],
        [
          2026,
          0.759000000190736
        ],
        [
          2027,
          0.73651893858716
        ],
        [
          2028,
          0.692980586830152
        ],
        [
          2029,
          0.645058155068015
        ],
        [
          2030,
          0.598768321396429
        ],
        [
          2031,
          0.55207208674255
        ],
        [
          2032,
          0.0
        ],
        [
          2033,
          0.0
        ],
        [
          2034,
          0.0
        ],
        [
          2035,
          0.0
        ],
        [
          2036,
          0.0
        ],
        [
          2037,
          0.0
        ],
        [
          2038,
          0.0
        ],
        [
          2039,
          0.0
        ],
        [
          2040,
          0.0
        ],
        [
          2041,
          0.0
        ],
        [
          2042,
          0.0
        ],
        [
          2043,
          0.0
        ],
        [
          2044,
          0.0
        ],
        [
          2045,
          0.0
        ]
      ]
    },
    {
      "seriesName": "DMD_TRA-F-HTRUCK-FCV",
      "seriesValues": [
        [
          2038,
          0.0
        ],
        [
          2039,
          0.0
        ],
        [
          2040,
          0.0
        ],
        [
          2041,
          0.0
        ],
        [
          2042,
          0.0
        ],
        [
          2043,
          0.0
        ],
        [
          2044,
          0.0
        ],
        [
          2045,
          0.0
        ],
        [
          2046,
          0.0
        ],
        [
          2047,
          0.0
        ],
        [
          2048,
          0.0
        ],
        [
          2049,
          0.0
        ],
        [
          2050,
          0.0
        ],
        [
          2051,
          1.08348482214698e-06
        ]
      ]
    }
  ]
}