{
  "name": "esb-bau~0001",
  "data": [
    {
      "seriesName": "TRAPL",
      "seriesValues": [
        [
          2018,
          27.131577548236173
        ],
        [
          2019,
          24.769203252609454
        ],
        [
          2020,
          17.917550783485947
        ],
        [
          2021,
          18.200537783828096
        ],
        [
          2022,
          18.849873753351204
        ],
        [
          2023,
          18.91853746780088
        ],
        [
          2024,
          19.391500914357017
        ],
        [
          2025,
          19.87628838195779
        ],
        [
          2026,
          20.373195600034325
        ],
        [
          2027,
          20.882525485527168
        ],
        [
          2028,
          21.404588629253784
        ],
        [
          2029,
          21.93970334409084
        ],
        [
          2030,
          22.48819592639462
        ],
        [
          2031,
          23.050400808092096
        ],
        [
          2032,
          23.626660840049798
        ],
        [
          2033,
          24.21732736194575
        ],
        [
          2034,
          24.822760547251015
        ],
        [
          2035,
          25.44332954636577
        ],
        [
          2036,
          26.079412768666554
        ],
        [
          2037,
          26.73139809522047
        ],
        [
          2038,
          27.39968305142258
        ],
        [
          2039,
          28.08467512593354
        ],
        [
          2040,
          28.786791998665844
        ],
        [
          2041,
          29.506461822017545
        ],
        [
          2042,
          30.244123357069824
        ],
        [
          2043,
          31.00022642971503
        ],
        [
          2044,
          31.775232085633686
        ],
        [
          2045,
          32.569612889055264
        ],
        [
          2046,
          33.383853207842876
        ],
        [
          2047,
          34.218449558253475
        ],
        [
          2048,
          35.0739107767529
        ],
        [
          2049,
          35.950758546354365
        ],
        [
          2050,
          36.849527502609405
        ],
        [
          2051,
          37.51191603503578
        ]
      ]
    },
    {
      "seriesName": "TRAPM",
      "seriesValues": [
        [
          2018,
          31.276118537205058
        ],
        [
          2019,
          31.984256441444774
        ],
        [
          2020,
          23.136777281983505
        ],
        [
          2021,
          27.703716024081466
        ],
        [
          2022,
          30.20220468470981
        ],
        [
          2023,
          30.31222110534713
        ],
        [
          2024,
          30.766904433257626
        ],
        [
          2025,
          31.22840796648874
        ],
        [
          2026,
          31.69683408666712
        ],
        [
          2027,
          32.17228659409779
        ],
        [
          2028,
          32.65487089669093
        ],
        [
          2029,
          33.14469395993266
        ],
        [
          2030,
          33.64186437574796
        ],
        [
          2031,
          34.146492327850815
        ],
        [
          2032,
          34.65868972689643
        ],
        [
          2033,
          35.17857007391227
        ],
        [
          2034,
          35.706248626367376
        ],
        [
          2035,
          36.241842341622416
        ],
        [
          2036,
          36.78546996106191
        ],
        [
          2037,
          37.337252017992896
        ],
        [
          2038,
          37.89731081941855
        ],
        [
          2039,
          38.46577047994268
        ],
        [
          2040,
          39.042757044366844
        ],
        [
          2041,
          39.628398423252996
        ],
        [
          2042,
          40.22282439131258
        ],
        [
          2043,
          40.82616672146168
        ],
        [
          2044,
          41.43855921759592
        ],
        [
          2045,
          42.06013760782782
        ],
        [
          2046,
          42.69103967606422
        ],
        [
          2047,
          43.33140527751724
        ],
        [
          2048,
          43.98137634562948
        ],
        [
          2049,
          44.64109699072496
        ],
        [
          2050,
          45.310713437978066
        ],
        [
          2051,
          45.583398970915844
        ]
      ]
    },
    {
      "seriesName": "TRAPS",
      "seriesValues": [
        [
          2018,
          14.55656110577129
        ],
        [
          2019,
          14.876398380145513
        ],
        [
          2020,
          10.76129178600343
        ],
        [
          2021,
          13.572515900556844
        ],
        [
          2022,
          14.056739109693499
        ],
        [
          2023,
          14.10794306632345
        ],
        [
          2024,
          14.284292365914776
        ],
        [
          2025,
          14.462845987226816
        ],
        [
          2026,
          14.643631562589224
        ],
        [
          2027,
          14.826676953263469
        ],
        [
          2028,
          15.0120104151784
        ],
        [
          2029,
          15.199660559308922
        ],
        [
          2030,
          15.38965631541006
        ],
        [
          2031,
          15.58202700606439
        ],
        [
          2032,
          15.776802357759516
        ],
        [
          2033,
          15.974012388531111
        ],
        [
          2034,
          16.17368755877783
        ],
        [
          2035,
          16.375858646272903
        ],
        [
          2036,
          16.58055686308828
        ],
        [
          2037,
          16.78781383478231
        ],
        [
          2038,
          16.997661514195052
        ],
        [
          2039,
          17.210132281703256
        ],
        [
          2040,
          17.42525894048474
        ],
        [
          2041,
          17.64307470049777
        ],
        [
          2042,
          17.863613123937625
        ],
        [
          2043,
          18.086908255777836
        ],
        [
          2044,
          18.312994604387544
        ],
        [
          2045,
          18.541907038579897
        ],
        [
          2046,
          18.77368087312776
        ],
        [
          2047,
          19.008351897564054
        ],
        [
          2048,
          19.245956281803675
        ],
        [
          2049,
          19.486530735600674
        ],
        [
          2050,
          19.730112362574573
        ],
        [
          2051,
          20.125870472622047
        ]
      ]
    }
  ]
}